vgmail
