Metadata-Version: 1.0
Name: vgmail
Version: 1.0.1
Summary: Python interface for gmail API
Home-page: UNKNOWN
Author: Vam Gan
Author-email: vamgan@cmu.edu
License: MIT
Platform: UNKNOWN
